backupman/__init__.py
backupman/backupman.py
backupman/rsync.py
backupman-1.1.2.dist-info/LICENSE
backupman-1.1.2.dist-info/METADATA
backupman-1.1.2.dist-info/WHEEL
backupman-1.1.2.dist-info/entry_points.txt
backupman-1.1.2.dist-info/top_level.txt
backupman-1.1.2.dist-info/RECORD
