Metadata-Version: 2.1
Name: backupman
Version: 1.1.2
Summary: Incremental Backup using RSYNC+SSH
Home-page: https://github.com/euikook/python-backupman
Author: euikook
Author-email: euikook@gmail.com
License: UNKNOWN
Keywords: rsync ssh cron incremental backup
Platform: UNKNOWN
Classifier: Development Status :: 4 - Beta
Classifier: Intended Audience :: Developers
Classifier: Intended Audience :: Information Technology
Classifier: Intended Audience :: System Administrators
Classifier: Topic :: System :: Archiving
Classifier: Topic :: System :: Archiving :: Backup
Classifier: Topic :: System :: Networking
Classifier: License :: OSI Approved :: MIT License
Classifier: Programming Language :: Python :: 2
Classifier: Programming Language :: Python :: 2.7
Classifier: Programming Language :: Python :: 3
Classifier: Programming Language :: Python :: 3.4
Classifier: Programming Language :: Python :: 3.5
Classifier: Programming Language :: Python :: 3.6
Requires-Dist: peppercorn
